{"errors":[],"warnings":[],"namedChunkGroups":{"app":{"chunks":[6,4,5,1],"assets":["webpack-runtime-9780baccea3874a41115.js","webpack-runtime-9780baccea3874a41115.js.map","framework-16534ddc5a576711dd15.js","framework-16534ddc5a576711dd15.js.map","styles.611e199a6abee5255bfc.css","styles-2c8cc638826070126d54.js","styles-2c8cc638826070126d54.js.map","app-163c8f9d227821fb7b6e.js","app-163c8f9d227821fb7b6e.js.map"],"children":{},"childAssets":{}},"component---src-pages-about-js":{"chunks":[0,2],"assets":["commons-401497d4b199a1f1e1d8.js","commons-401497d4b199a1f1e1d8.js.map","component---src-pages-about-js-c4d2789ff3aef3e42093.js","component---src-pages-about-js-c4d2789ff3aef3e42093.js.map"],"children":{},"childAssets":{}},"component---src-pages-index-js":{"chunks":[0,3],"assets":["commons-401497d4b199a1f1e1d8.js","commons-401497d4b199a1f1e1d8.js.map","component---src-pages-index-js-2c180d34dbdac1b1774b.js","component---src-pages-index-js-2c180d34dbdac1b1774b.js.map"],"children":{},"childAssets":{}}},"assetsByChunkName":{"app":["webpack-runtime-9780baccea3874a41115.js","framework-16534ddc5a576711dd15.js","styles.611e199a6abee5255bfc.css","styles-2c8cc638826070126d54.js","app-163c8f9d227821fb7b6e.js"],"component---src-pages-about-js":["commons-401497d4b199a1f1e1d8.js","component---src-pages-about-js-c4d2789ff3aef3e42093.js"],"component---src-pages-index-js":["commons-401497d4b199a1f1e1d8.js","component---src-pages-index-js-2c180d34dbdac1b1774b.js"]}}